astk/ChromHMM.jar
astk/ChromHMM.py
astk/__init__.py
astk/constant.py
astk/ctypes.py
astk/lazy_loader.py
astk/types.py
astk/R/ChromHMM_hm.R
astk/R/CoSpliceNet.R
astk/R/barplot.R
astk/R/dl_keggdata.R
astk/R/enrich.R
astk/R/enrichCompare.R
astk/R/epiFeature.R
astk/R/epiProfile.R
astk/R/gsea.R
astk/R/gseaPlot.R
astk/R/heatmap.R
astk/R/install.R
astk/R/makeTxDb.R
astk/R/motifEnrich.R
astk/R/motifFind.R
astk/R/motifMap.R
astk/R/motifPlot.R
astk/R/pca.R
astk/R/seqLogo.R
astk/R/signalCompare.R
astk/R/signalHeatmap.R
astk/R/signalProfile.R
astk/R/upset.R
astk/R/utils.R
astk/R/volcano.R
astk/cli/__init__.py
astk/cli/aliases.ini
astk/cli/as_event.py
astk/cli/config.py
astk/cli/draw.py
astk/cli/epi.py
astk/cli/experiment.py
astk/cli/gsea.py
astk/cli/ml.py
astk/cli/motif.py
astk/cli/net.py
astk/cli/seqfeature.py
astk/cli/suppa.py
astk/cli/utils.py
astk/data/maxent/ss3_score.json
astk/data/maxent/ss5seq_score.json
astk/data/motif/ATtRACT/Arabidopsis_thaliana.meme
astk/data/motif/ATtRACT/Aspergillus_nidulans.meme
astk/data/motif/ATtRACT/Bombyx_mori.meme
astk/data/motif/ATtRACT/Bos_taurus.meme
astk/data/motif/ATtRACT/Brachypodium_distachyon.meme
astk/data/motif/ATtRACT/Caenorhabditis_elegans.meme
astk/data/motif/ATtRACT/Chaetomium_thermophilum.meme
astk/data/motif/ATtRACT/Cricetulus_griseus.meme
astk/data/motif/ATtRACT/Danio_rerio.meme
astk/data/motif/ATtRACT/Drosophila_melanogaster.meme
astk/data/motif/ATtRACT/Gallus_gallus.meme
astk/data/motif/ATtRACT/Homo_sapiens.meme
astk/data/motif/ATtRACT/Leishmania_major.meme
astk/data/motif/ATtRACT/Mesocricetus_auratus.meme
astk/data/motif/ATtRACT/Mus_musculus.meme
astk/data/motif/ATtRACT/Naegleria_gruberi.meme
astk/data/motif/ATtRACT/Nematostella_vectensis.meme
astk/data/motif/ATtRACT/Neurospora_crassa.meme
astk/data/motif/ATtRACT/Oryctolagus_cuniculus.meme
astk/data/motif/ATtRACT/Oryzias_latipes.meme
astk/data/motif/ATtRACT/Ostreococcus_tauri.meme
astk/data/motif/ATtRACT/Physcomitrella_patens.meme
astk-0.1.3.dist-info/LICENSE
astk-0.1.3.dist-info/METADATA
astk-0.1.3.dist-info/WHEEL
astk-0.1.3.dist-info/entry_points.txt
astk-0.1.3.dist-info/top_level.txt
astk-0.1.3.dist-info/RECORD
