Metadata-Version: 2.1
Name: astk
Version: 0.1.3
Summary: A comprehensive toolkit for alternative splicing analysis
Home-page: https://github.com/huang-sh/astk/
Author: huangsh
Author-email: hsh-me@outlook.com
License-File: LICENSE
Requires-Dist: click (>=8.0.0)
Requires-Dist: pandas (>=1.3.0)
Requires-Dist: matplotlib (>=3.4.0)
Requires-Dist: scikit-learn (>=0.24.0)
Requires-Dist: statsmodels (>=0.12.0)
Requires-Dist: gseapy (==0.10.8)
Requires-Dist: statannotations
Requires-Dist: seaborn
Requires-Dist: tqdm
Requires-Dist: pysam
Requires-Dist: pyfaidx
Requires-Dist: nease
Requires-Dist: biopython
Requires-Dist: pyecharts
Requires-Dist: click-option-group
